lightruler/__init__.py
luban/__init__.py
lightRuler-0.0.1.dist-info/LICENSE
lightRuler-0.0.1.dist-info/METADATA
lightRuler-0.0.1.dist-info/WHEEL
lightRuler-0.0.1.dist-info/top_level.txt
lightRuler-0.0.1.dist-info/RECORD
