Metadata-Version: 2.1
Name: lightRuler
Version: 0.0.1
Summary: A Python pattern matching engine library
Home-page: https://github.com/smilelight/lightRuler
Author: lightsmile
Author-email: iamlightsmile@gmail.com
License: Apache-2.0
Platform: UNKNOWN
Classifier: Development Status :: 4 - Beta
Classifier: Operating System :: OS Independent
Classifier: Intended Audience :: Developers
Classifier: Programming Language :: Python :: 3.7
Classifier: Programming Language :: Python :: 3.8
Classifier: Topic :: Software Development :: Libraries
Requires-Dist: tqdm
Requires-Dist: lightutils
